moe_transcode/__init__.py
moe_transcode/transcode_core.py
moe_transcode-1.1.1.dist-info/LICENSE
moe_transcode-1.1.1.dist-info/METADATA
moe_transcode-1.1.1.dist-info/WHEEL
moe_transcode-1.1.1.dist-info/entry_points.txt
moe_transcode-1.1.1.dist-info/RECORD
